vibe_tools/__init__.py
vibe_tools/cli.py
vibe_tools/core/__init__.py
vibe_tools/core/detector.py
vibe_tools/core/installer.py
vibe_tools/tools/__init__.py
vibe_tools/ui/__init__.py
vibe_tools/ui/display.py
vibe_tools/ui/menu.py
vibe_tools/utils/__init__.py
vibe_env_kit-0.1.0.dist-info/METADATA
vibe_env_kit-0.1.0.dist-info/WHEEL
vibe_env_kit-0.1.0.dist-info/entry_points.txt
vibe_env_kit-0.1.0.dist-info/RECORD
