Metadata-Version: 2.4
Name: vibe-env-kit
Version: 0.1.0
Summary: Vibe 环境配置工具包，一键安装开发环境、编程依赖和工具链
Project-URL: Homepage, https://github.com/vibe-tools/vibe-env-kit
Project-URL: Documentation, https://vibe-env-kit.readthedocs.io/
Project-URL: Repository, https://github.com/vibe-tools/vibe-env-kit.git
Project-URL: Bug Tracker, https://github.com/vibe-tools/vibe-env-kit/issues
Author-email: Vibe Tools Team <team@vibe-tools.dev>
License: MIT
Keywords: cli,development,env-kit,environment,installer,setup,tools,vibe
Classifier: Development Status :: 3 - Alpha
Classifier: Intended Audience :: Developers
Classifier: License :: OSI Approved :: MIT License
Classifier: Operating System :: OS Independent
Classifier: Programming Language :: Python :: 3
Classifier: Programming Language :: Python :: 3.8
Classifier: Programming Language :: Python :: 3.9
Classifier: Programming Language :: Python :: 3.10
Classifier: Programming Language :: Python :: 3.11
Classifier: Programming Language :: Python :: 3.12
Classifier: Topic :: Software Development :: Libraries :: Python Modules
Classifier: Topic :: System :: Systems Administration
Classifier: Topic :: Utilities
Requires-Python: >=3.8
Requires-Dist: click>=8.0.0
Requires-Dist: packaging>=21.0
Requires-Dist: requests>=2.25.0
Requires-Dist: rich>=13.0.0
Requires-Dist: toml>=0.10.2
Requires-Dist: typing-extensions>=4.0.0; python_version < '3.10'
Provides-Extra: dev
Requires-Dist: black>=22.0.0; extra == 'dev'
Requires-Dist: mypy>=1.0.0; extra == 'dev'
Requires-Dist: pre-commit>=2.20.0; extra == 'dev'
Requires-Dist: pytest-cov>=4.0.0; extra == 'dev'
Requires-Dist: pytest>=7.0.0; extra == 'dev'
Requires-Dist: ruff>=0.1.0; extra == 'dev'
